vali/__init__.py
vali/apps.py
vali/charts.py
vali/counters.py
vali/decorator.py
vali/urls.py
vali/views.py
vali/widgets.py
vali/static/img/counter.png
vali/static/vali/assets/vali.css
vali/static/vali/assets/vali.js
vali/static/vali/assets/img/logo.jpg
vali/static/vali/assets/img/logo.png
vali/static/vali/assets/js/bootstrap.min.js
vali/static/vali/assets/js/jquery-3.2.1.min.js
vali/static/vali/assets/js/main.js
vali/static/vali/assets/js/popper.min.js
vali/static/vali/assets/js/plugins/bootstrap-datepicker.min.js
vali/static/vali/assets/js/plugins/bootstrap-notify.min.js
vali/static/vali/assets/js/plugins/bootstrap-treeview.min.css
vali/static/vali/assets/js/plugins/bootstrap-treeview.min.js
vali/static/vali/assets/js/plugins/chart.js
vali/static/vali/assets/js/plugins/dataTables.bootstrap.min.js
vali/static/vali/assets/js/plugins/fullcalendar.min.js
vali/static/vali/assets/js/plugins/jquery-ui.custom.min.js
vali/static/vali/assets/js/plugins/jquery.dataTables.min.js
vali/static/vali/assets/js/plugins/jquery.vmap.min.js
vali/static/vali/assets/js/plugins/jquery.vmap.sampledata.js
vali/static/vali/assets/js/plugins/jquery.vmap.world.js
vali/static/vali/assets/js/plugins/moment.min.js
vali/static/vali/assets/js/plugins/pace.min.js
vali/static/vali/assets/js/plugins/select2.min.js
vali/static/vali/assets/js/plugins/sweetalert.min.js
vali/static/vali/themes/blue/main.css
vali/static/vali/themes/brown/main.css
vali/static/vali/themes/default/main.css
vali/static/vali/themes/green/main.css
vali/static/vali/themes/purple/main.css
vali/templates/charts.html
vali/templates/counters.html
vali/templates/dashboard.html
vali/templates/admin/404.html
vali/templates/admin/500.html
vali/templates/admin/actions.html
vali/templates/admin/app_index.html
vali/templates/admin/base.html
vali/templates/admin/base_site.html
vali/templates/admin/change_form.html
vali/templates/admin/change_list.html
vali/templates/admin/change_list_results.html
vali/templates/admin/date_hierarchy.html
django_admin_vali-0.2.2.dist-info/LICENSE
django_admin_vali-0.2.2.dist-info/METADATA
django_admin_vali-0.2.2.dist-info/WHEEL
django_admin_vali-0.2.2.dist-info/top_level.txt
django_admin_vali-0.2.2.dist-info/RECORD
