Metadata-Version: 2.1
Name: django-admin-vali
Version: 0.2.2
Summary: Django Admin with Vali theme
Home-page: https://github.com/JchJ/Vali-Django-Admin
Author: Juan Carlo Henriques Junger
Author-email: juancarlo.h.junger@hotmail.com
License: MIT License
Platform: UNKNOWN
Classifier: Programming Language :: Python
Classifier: Programming Language :: Python :: 3
Classifier: Programming Language :: Python :: 3.5
Classifier: Programming Language :: Python :: 3.6
Classifier: License :: OSI Approved :: MIT License
Classifier: Operating System :: OS Independent
Classifier: Environment :: Web Environment
Classifier: Framework :: Django
Classifier: Framework :: Django :: 2.1
Classifier: Intended Audience :: Developers
Classifier: Topic :: Internet :: WWW/HTTP
Classifier: Topic :: Internet :: WWW/HTTP :: Dynamic Content
